speedestpy-0.1.0.dist-info/METADATA
speedestpy-0.1.0.dist-info/WHEEL
speedestpy-0.1.0.dist-info/licenses/LICENSE
speedestpy.libs/libgcc_s-e52197c3.so.1
speedestpy/__init__.py
speedestpy/py.py
speedestpy/speedestpy.cpython-312-aarch64-linux-musl.so
speedestpy-0.1.0.dist-info/RECORD
