Metadata-Version: 2.4
Name: speedestpy
Version: 0.1.0
Classifier: License :: OSI Approved :: MIT License
Classifier: Programming Language :: Rust
Classifier: Programming Language :: Python :: 3
Classifier: Programming Language :: Python :: Implementation :: CPython
Classifier: Programming Language :: Python :: Implementation :: PyPy
Requires-Dist: numpy >=1.21.0
License-File: LICENSE
Summary: Tests to improve performance in computationally intensive tasks.
Author-email: Guillaume Havard <guill.havard@gmail.com>
Requires-Python: >=3.12
Project-URL: Homepage, https://github.com/guillaume-havard/speedestpy
Project-URL: Issues, https://github.com/guillaume-havard/speedestpy/issues
